sf_etl_py3/Utils.py
sf_etl_py3/__init__.py
sf_etl_py3/bot/__init__.py
sf_etl_py3/bot/ding_bot.py
sf_etl_py3/xml/__init__.py
sf_etl_py3/xml/kettle_xml.py
sf_etl_py3/xml/sf_xml.py
sf_etl_py3/xml/tableau_xml.py
test_sf_etl_py3-0.0.11.dist-info/LICENSE
test_sf_etl_py3-0.0.11.dist-info/METADATA
test_sf_etl_py3-0.0.11.dist-info/WHEEL
test_sf_etl_py3-0.0.11.dist-info/top_level.txt
test_sf_etl_py3-0.0.11.dist-info/RECORD
