Metadata-Version: 2.1
Name: test-sf-etl-py3
Version: 0.0.11
Summary: surfin test
Home-page: 
Author: iszzZ
Author-email: xxx@foxmail.com
Classifier: Programming Language :: Python :: 3
Classifier: License :: OSI Approved :: MIT License
Classifier: Operating System :: OS Independent
Requires-Python: >=3.7
License-File: LICENSE
Requires-Dist: imgkit (==1.2.2)
Requires-Dist: oss2 (==2.16.0)
Requires-Dist: psycopg2-binary (==2.8.6)
Requires-Dist: pyecharts (==1.9.1)
Requires-Dist: requests
Requires-Dist: PyMySQL (==1.0.2)
